README
setup.py
lammps_tools/__init__.py
lammps_tools.egg-info/PKG-INFO
lammps_tools.egg-info/SOURCES.txt
lammps_tools.egg-info/dependency_links.txt
lammps_tools.egg-info/top_level.txt
lammps_tools/data_processing/__init__.py
lammps_tools/data_processing/dump.py
lammps_tools/data_processing/fix.py
lammps_tools/data_processing/log.py
lammps_tools/model_builder/GP_generator.py
lammps_tools/model_builder/__init__.py
lammps_tools/model_builder/polymer_generator.py
lammps_tools/test/__init__.py