Metadata-Version: 1.2
Name: lammps-tools
Version: 1.0.8
Summary: lammps data process tools.
Home-page: https://github.com/Roy-Kid/lammps-tools
Author: Roy-Kid
Author-email: lijichen365@126.com
License: LICENSE
Platform: UNKNOWN
Requires-Python: >=3
